varscore/__init__.py
varscore/annotations.py
varscore/chrombpnet_utils.py
varscore/variant_scoring_functions.py
varscore-0.0.1a0.dist-info/METADATA
varscore-0.0.1a0.dist-info/WHEEL
varscore-0.0.1a0.dist-info/top_level.txt
varscore-0.0.1a0.dist-info/RECORD
